README.md
setup.cfg
setup.py
yb_client/api.py
yb_client/commands.py
yb_client/file.py
yb_client/output.py
yb_client.egg-info/PKG-INFO
yb_client.egg-info/SOURCES.txt
yb_client.egg-info/dependency_links.txt
yb_client.egg-info/entry_points.txt
yb_client.egg-info/requires.txt
yb_client.egg-info/top_level.txt