Metadata-Version: 1.1
Name: yb-client
Version: 1.0.1
Summary: Yottab-Client is a command-line interface to interact with the Yottab server to create and manage workspaces and applications.
Home-page: https://github.com/yottab-io/yb-client
Author: Yottab
Author-email: admin@yottab.io
License: GNU General Public License v3.0
Download-URL: https://github.com/yottab-io/yb-client/archive/refs/tags/v1.0.1.tar.gz
Keywords: yottab,yottab client,command-line
Platform: UNKNOWN
Classifier: Development Status :: 3 - Alpha
Classifier: Intended Audience :: Developers
Classifier: Topic :: Scientific/Engineering :: Human Machine Interfaces
Classifier: License :: OSI Approved :: GNU General Public License v3 (GPLv3)
Classifier: Programming Language :: Python :: 3
Classifier: Programming Language :: Python :: 3.4
Classifier: Programming Language :: Python :: 3.5
Classifier: Programming Language :: Python :: 3.6
Classifier: Programming Language :: Python :: 3.8
